funnelplot/__init__.py
funnelplot/funnelplot.py
funnelpy/__init__.py
funnelpy/funnelplot.py
funnelpy/funnelpy.py
funnelpy/sigmas.py
funnelpy-0.8.0.dist-info/LICENSE
funnelpy-0.8.0.dist-info/METADATA
funnelpy-0.8.0.dist-info/WHEEL
funnelpy-0.8.0.dist-info/top_level.txt
funnelpy-0.8.0.dist-info/RECORD
