Metadata-Version: 2.1
Name: funnelpy
Version: 0.8.0
Summary: Create a funnel plot.
Home-page: https://github.com/lyonjust/funnelpy
Author: Justin Lyons
Author-email: lyonjust@outlook.com
License: MIT
Platform: UNKNOWN
Classifier: License :: OSI Approved :: MIT License
Classifier: Programming Language :: Python :: 3
Classifier: Programming Language :: Python :: 3.7
Requires-Dist: pandas
Requires-Dist: matplotlib
Requires-Dist: seaborn
